template_file_parser/__init__.py
template_file_parser/template.py
template_file_parser-0.14.dist-info/DESCRIPTION.rst
template_file_parser-0.14.dist-info/METADATA
template_file_parser-0.14.dist-info/RECORD
template_file_parser-0.14.dist-info/WHEEL
template_file_parser-0.14.dist-info/metadata.json
template_file_parser-0.14.dist-info/top_level.txt
