Metadata-Version: 2.0
Name: template-file-parser
Version: 0.14
Summary: Tiny wrapper over string templates which works with files
Home-page: https://github.com/david-gang/template-file-parser
Author: David Gang
Author-email: michaelgang@gmail.com
License: Apache 2.0
Platform: UNKNOWN
Requires-Python: >=3.4
